{"id":302,"title":"Cambodian Flooding","description":"In mid-August 2011, unusually heavy rains over the upper Mekong River in Laos and Thailand led to severe flooding in Cambodia. According to the Phnom Penh Post, thousands of people had been left homeless from rising flood waters. Vegetation is displayed in red, bare ground is light brown, and water is black or dark green where it is relatively clear, and green-blue where it carries large amounts of sediment.","sharing_url":"http://wlppr.cc/sharing/wallpaper/302?s=94ba2204e61613af6a9ffedd872b7691","created_at":"2016-02-03 13:17:26 UTC","updated_at":"2016-02-03 13:21:32 UTC","link":"http://www.jpl.nasa.gov/spaceimages/details.php?id=PIA14765","copyright":"© Jet Propulsion Laboratory (JPL, NASA, Caltech, jpl.nasa.gov)","copyright_details":"GSFC/METI/ERSDAC/JAROS, and U.S./Japan ASTER Science Team.","origin":{"name":"JPL","link":"http://www.jpl.nasa.gov","copyright":"© Jet Propulsion Laboratory (JPL, NASA, Caltech, jpl.nasa.gov)"},"theme":{"name":"FALSE – COLOR","description":"Satellites show what human eyes can't see"},"image_format":{"original":"png","parallax":null}}